README.md
setup.py
sqline.py
sqline.egg-info/PKG-INFO
sqline.egg-info/SOURCES.txt
sqline.egg-info/dependency_links.txt
sqline.egg-info/entry_points.txt
sqline.egg-info/not-zip-safe
sqline.egg-info/requires.txt
sqline.egg-info/top_level.txt