Metadata-Version: 1.0
Name: sqline
Version: 0.2.0
Summary: Command line tool to perform database queries.
Home-page: https://github.com/davidgasquez/sqline
Author: David Gasquez
Author-email: davidgasquez@gmail.com
License: MIT license
Keywords: sqline
Platform: UNKNOWN
